farn/__init__.py
farn/farn.py
farn/py.typed
farn/cli/__init__.py
farn/cli/__main__.py
farn/core/__init__.py
farn/core/case.py
farn/core/parameter.py
farn/run/__init__.py
farn/run/batchProcess.py
farn/run/subProcess.py
farn/run/cli/__init__.py
farn/run/cli/batchProcess.py
farn/run/utils/__init__.py
farn/run/utils/threading.py
farn/sampling/__init__.py
farn/sampling/sampling.py
farn/utils/__init__.py
farn/utils/logging.py
farn/utils/os.py
farn-0.4.2.dist-info/METADATA
farn-0.4.2.dist-info/WHEEL
farn-0.4.2.dist-info/entry_points.txt
farn-0.4.2.dist-info/licenses/LICENSE
farn-0.4.2.dist-info/RECORD
