Metadata-Version: 2.4
Name: farn
Version: 0.4.2
Summary: Python package to generate an n-dimensional case folder structure applying linear and spatial sampling strategies.
Project-URL: Homepage, https://github.com/dnv-opensource/farn
Project-URL: Documentation, https://dnv-opensource.github.io/farn/README.html
Project-URL: Repository, https://github.com/dnv-opensource/farn.git
Project-URL: Issues, https://github.com/dnv-opensource/farn/issues
Project-URL: Changelog, https://github.com/dnv-opensource/farn/blob/main/CHANGELOG.md
Author-email: Frank Lumpitzsch <frank.lumpitzsch@dnv.com>, Claas Rostock <claas.rostock@dnv.com>, Seunghyeon Yoo <seunghyeon.yoo@dnv.com>
Maintainer-email: Claas Rostock <claas.rostock@dnv.com>
License: MIT License
License-File: LICENSE
Keywords: OSP,farn,fmi
Classifier: Development Status :: 5 - Production/Stable
Classifier: Environment :: Console
Classifier: Intended Audience :: Developers
Classifier: Intended Audience :: Science/Research
Classifier: License :: OSI Approved :: MIT License
Classifier: Operating System :: MacOS
Classifier: Operating System :: Microsoft :: Windows
Classifier: Operating System :: POSIX :: Linux
Classifier: Programming Language :: Python :: 3.11
Classifier: Programming Language :: Python :: 3.12
Classifier: Programming Language :: Python :: 3.13
Classifier: Programming Language :: Python :: 3.14
Classifier: Topic :: Scientific/Engineering
Classifier: Topic :: Software Development :: Libraries :: Python Modules
Requires-Python: <3.15,>=3.11
Requires-Dist: dictio>=0.4.2
Requires-Dist: hilbertcurve>=2.0.5
Requires-Dist: lxml>=6.0
Requires-Dist: matplotlib>=3.10
Requires-Dist: numpy>=2.3
Requires-Dist: ospx>=0.3.2
Requires-Dist: pandas>=2.3
Requires-Dist: pillow>=12.0
Requires-Dist: psutil>=5.9
Requires-Dist: pydoe3>=1.6
Requires-Dist: scipy>=1.16
